nepsense/Nepse.py
nepsense/Stock.py
nepsense/__init__.py
nepsense/company_list.csv
nepsense/data.py
nepsense/index.txt
nepsense/priceof
nepsense-0.69.420.data/scripts/priceof
nepsense-0.69.420.dist-info/LICENSE
nepsense-0.69.420.dist-info/METADATA
nepsense-0.69.420.dist-info/WHEEL
nepsense-0.69.420.dist-info/top_level.txt
nepsense-0.69.420.dist-info/RECORD
