Metadata-Version: 2.1
Name: nepsense
Version: 0.69.420
Summary: Complete NepalStock solution in command line
Home-page: https://github.com/buddha231/NEPSENSE
Author: Buddha Gautam
Author-email: buddhagautam231@gmail.com
License: UNKNOWN
Keywords: nepsense nepalstock stonk buddha python package buddha69
Platform: UNKNOWN
Classifier: Programming Language :: Python :: 3
Classifier: License :: OSI Approved :: MIT License
Classifier: Operating System :: OS Independent
Requires-Python: >=3
License-File: LICENSE
Requires-Dist: certifi (==2021.5.30)
Requires-Dist: chardet (==4.0.0)
Requires-Dist: colorama (==0.4.4)
Requires-Dist: idna (==2.10)
Requires-Dist: numpy (==1.20.3)
Requires-Dist: pandas (==1.2.4)
Requires-Dist: python-dateutil (==2.8.1)
Requires-Dist: pytz (==2021.1)
Requires-Dist: requests (==2.25.1)
Requires-Dist: six (==1.16.0)
Requires-Dist: tabulate (==0.8.9)
Requires-Dist: urllib3 (==1.26.5)
